{
  "report_version": "v2",
  "generated_at_utc": "2026-03-30T00:18:10Z",
  "report_date_jst": "2026-03-30T08:00:00+09:00",
  "week_window": {
    "start": "20260323",
    "end": "20260327"
  },
  "business_day_count": 5,
  "annotation_coverage": {
    "total_observations": 20,
    "confirmed_annotation_count": 0,
    "pending_annotation_count": 0,
    "unlabeled_count": 20,
    "annotation_coverage_rate": 0.0
  },
  "strategy_metrics": [
    {
      "observation_count": 5,
      "direction_hit_count": 0,
      "direction_hit_rate": "0.0",
      "range_hit_count": "",
      "range_hit_rate": "",
      "state_proxy_hit_count": "",
      "state_proxy_hit_rate": "",
      "mean_close_error_bp": "",
      "median_close_error_bp": "",
      "mean_magnitude_error_bp": "",
      "strategy_kind": "baseline_prev_day_direction"
    },
    {
      "observation_count": 5,
      "direction_hit_count": 0,
      "direction_hit_rate": "0.0",
      "range_hit_count": "",
      "range_hit_rate": "",
      "state_proxy_hit_count": "",
      "state_proxy_hit_rate": "",
      "mean_close_error_bp": "",
      "median_close_error_bp": "",
      "mean_magnitude_error_bp": "",
      "strategy_kind": "baseline_random_walk"
    },
    {
      "observation_count": 5,
      "direction_hit_count": 0,
      "direction_hit_rate": "0.0",
      "range_hit_count": "",
      "range_hit_rate": "",
      "state_proxy_hit_count": "",
      "state_proxy_hit_rate": "",
      "mean_close_error_bp": "",
      "median_close_error_bp": "",
      "mean_magnitude_error_bp": "",
      "strategy_kind": "baseline_simple_technical"
    },
    {
      "observation_count": 5,
      "direction_hit_count": 0,
      "direction_hit_rate": "0.0",
      "range_hit_count": "",
      "range_hit_rate": "",
      "state_proxy_hit_count": "",
      "state_proxy_hit_rate": "",
      "mean_close_error_bp": "",
      "median_close_error_bp": "",
      "mean_magnitude_error_bp": "",
      "strategy_kind": "ugh"
    }
  ],
  "slice_metrics": [
    {
      "observation_count": 5,
      "direction_hit_count": 0,
      "direction_hit_rate": "0.0",
      "range_hit_count": "",
      "range_hit_rate": "",
      "state_proxy_hit_count": "",
      "state_proxy_hit_rate": "",
      "mean_close_error_bp": "",
      "median_close_error_bp": "",
      "mean_magnitude_error_bp": "",
      "slice_dimension": "regime_label",
      "strategy_kind": "baseline_prev_day_direction",
      "label": "unlabeled"
    },
    {
      "observation_count": 5,
      "direction_hit_count": 0,
      "direction_hit_rate": "0.0",
      "range_hit_count": "",
      "range_hit_rate": "",
      "state_proxy_hit_count": "",
      "state_proxy_hit_rate": "",
      "mean_close_error_bp": "",
      "median_close_error_bp": "",
      "mean_magnitude_error_bp": "",
      "slice_dimension": "regime_label",
      "strategy_kind": "baseline_random_walk",
      "label": "unlabeled"
    },
    {
      "observation_count": 5,
      "direction_hit_count": 0,
      "direction_hit_rate": "0.0",
      "range_hit_count": "",
      "range_hit_rate": "",
      "state_proxy_hit_count": "",
      "state_proxy_hit_rate": "",
      "mean_close_error_bp": "",
      "median_close_error_bp": "",
      "mean_magnitude_error_bp": "",
      "slice_dimension": "regime_label",
      "strategy_kind": "baseline_simple_technical",
      "label": "unlabeled"
    },
    {
      "observation_count": 5,
      "direction_hit_count": 0,
      "direction_hit_rate": "0.0",
      "range_hit_count": "",
      "range_hit_rate": "",
      "state_proxy_hit_count": "",
      "state_proxy_hit_rate": "",
      "mean_close_error_bp": "",
      "median_close_error_bp": "",
      "mean_magnitude_error_bp": "",
      "slice_dimension": "regime_label",
      "strategy_kind": "ugh",
      "label": "unlabeled"
    },
    {
      "observation_count": 5,
      "direction_hit_count": 0,
      "direction_hit_rate": "0.0",
      "range_hit_count": "",
      "range_hit_rate": "",
      "state_proxy_hit_count": "",
      "state_proxy_hit_rate": "",
      "mean_close_error_bp": "",
      "median_close_error_bp": "",
      "mean_magnitude_error_bp": "",
      "slice_dimension": "volatility_label",
      "strategy_kind": "baseline_prev_day_direction",
      "label": "unlabeled"
    },
    {
      "observation_count": 5,
      "direction_hit_count": 0,
      "direction_hit_rate": "0.0",
      "range_hit_count": "",
      "range_hit_rate": "",
      "state_proxy_hit_count": "",
      "state_proxy_hit_rate": "",
      "mean_close_error_bp": "",
      "median_close_error_bp": "",
      "mean_magnitude_error_bp": "",
      "slice_dimension": "volatility_label",
      "strategy_kind": "baseline_random_walk",
      "label": "unlabeled"
    },
    {
      "observation_count": 5,
      "direction_hit_count": 0,
      "direction_hit_rate": "0.0",
      "range_hit_count": "",
      "range_hit_rate": "",
      "state_proxy_hit_count": "",
      "state_proxy_hit_rate": "",
      "mean_close_error_bp": "",
      "median_close_error_bp": "",
      "mean_magnitude_error_bp": "",
      "slice_dimension": "volatility_label",
      "strategy_kind": "baseline_simple_technical",
      "label": "unlabeled"
    },
    {
      "observation_count": 5,
      "direction_hit_count": 0,
      "direction_hit_rate": "0.0",
      "range_hit_count": "",
      "range_hit_rate": "",
      "state_proxy_hit_count": "",
      "state_proxy_hit_rate": "",
      "mean_close_error_bp": "",
      "median_close_error_bp": "",
      "mean_magnitude_error_bp": "",
      "slice_dimension": "volatility_label",
      "strategy_kind": "ugh",
      "label": "unlabeled"
    },
    {
      "observation_count": 5,
      "direction_hit_count": 0,
      "direction_hit_rate": "0.0",
      "range_hit_count": "",
      "range_hit_rate": "",
      "state_proxy_hit_count": "",
      "state_proxy_hit_rate": "",
      "mean_close_error_bp": "",
      "median_close_error_bp": "",
      "mean_magnitude_error_bp": "",
      "slice_dimension": "intervention_risk",
      "strategy_kind": "baseline_prev_day_direction",
      "label": "unlabeled"
    },
    {
      "observation_count": 5,
      "direction_hit_count": 0,
      "direction_hit_rate": "0.0",
      "range_hit_count": "",
      "range_hit_rate": "",
      "state_proxy_hit_count": "",
      "state_proxy_hit_rate": "",
      "mean_close_error_bp": "",
      "median_close_error_bp": "",
      "mean_magnitude_error_bp": "",
      "slice_dimension": "intervention_risk",
      "strategy_kind": "baseline_random_walk",
      "label": "unlabeled"
    },
    {
      "observation_count": 5,
      "direction_hit_count": 0,
      "direction_hit_rate": "0.0",
      "range_hit_count": "",
      "range_hit_rate": "",
      "state_proxy_hit_count": "",
      "state_proxy_hit_rate": "",
      "mean_close_error_bp": "",
      "median_close_error_bp": "",
      "mean_magnitude_error_bp": "",
      "slice_dimension": "intervention_risk",
      "strategy_kind": "baseline_simple_technical",
      "label": "unlabeled"
    },
    {
      "observation_count": 5,
      "direction_hit_count": 0,
      "direction_hit_rate": "0.0",
      "range_hit_count": "",
      "range_hit_rate": "",
      "state_proxy_hit_count": "",
      "state_proxy_hit_rate": "",
      "mean_close_error_bp": "",
      "median_close_error_bp": "",
      "mean_magnitude_error_bp": "",
      "slice_dimension": "intervention_risk",
      "strategy_kind": "ugh",
      "label": "unlabeled"
    }
  ],
  "provider_health_summary": {
    "total_runs": 7,
    "providers": {
      "alpha_vantage": 7
    },
    "fallback_adjustment_count": 0,
    "lag_count": 0,
    "success_count": 2,
    "failed_count": 0,
    "skipped_count": 5
  },
  "observation_count": 20,
  "generated_artifact_paths": [
    "/home/runner/work/ugh-quantamental/ugh-quantamental/data/csv/analytics/weekly/20260330/weekly_report.json",
    "/home/runner/work/ugh-quantamental/ugh-quantamental/data/csv/analytics/weekly/20260330/weekly_report.md",
    "/home/runner/work/ugh-quantamental/ugh-quantamental/data/csv/analytics/weekly/20260330/weekly_strategy_metrics.csv",
    "/home/runner/work/ugh-quantamental/ugh-quantamental/data/csv/analytics/weekly/20260330/weekly_slice_metrics.csv"
  ]
}
